fsam/__init__.py
fsam/fsam_fit.py
fsam/penalized_group_lasso.py
fsam/sop.py
tests/__init__.py
tests/test_bounds.py
tests/test_identifiabilty_conditions.py
tests/test_penalised_group_lasso.py
tests/test_reparametrization.py
tests/test_solution.py
tests/test_sop.py
tests/test_warm_start.py
fsam-0.1.1.dist-info/LICENSE
fsam-0.1.1.dist-info/METADATA
fsam-0.1.1.dist-info/WHEEL
fsam-0.1.1.dist-info/top_level.txt
fsam-0.1.1.dist-info/RECORD
