Metadata-Version: 2.1
Name: fsam
Version: 0.1.1
Home-page: https://github.com/ManuelNavarroGarcia/fsam/
Download-URL: https://github.com/ManuelNavarroGarcia/fsam/archive/refs/tags/0.1.1.tar.gz
Author: Manuel Navarro García
Author-email: manuelnavarrogithub@gmail.com
License: MIT
Requires-Python: >=3.9
License-File: LICENSE
Requires-Dist: matplotlib
Requires-Dist: numpy
Requires-Dist: pandas
Requires-Dist: cpsplines
Requires-Dist: typer
Requires-Dist: gurobipy >=10.0.0
Requires-Dist: scikit-learn
Requires-Dist: statsmodels
Requires-Dist: tqdm
Provides-Extra: dev
Requires-Dist: black ; extra == 'dev'
Requires-Dist: ipykernel ; extra == 'dev'
Requires-Dist: pip-tools ; extra == 'dev'
Requires-Dist: pytest ; extra == 'dev'
Requires-Dist: ipywidgets ; extra == 'dev'
